fltools/__init__.py
fltools/__main__.py
fltools/filelist_listener.py
fltools/filelist_parser.py
fltools/filelist_token.py
fltools-0.0.1.3357237312.dist-info/LICENSE
fltools-0.0.1.3357237312.dist-info/METADATA
fltools-0.0.1.3357237312.dist-info/WHEEL
fltools-0.0.1.3357237312.dist-info/entry_points.txt
fltools-0.0.1.3357237312.dist-info/top_level.txt
fltools-0.0.1.3357237312.dist-info/RECORD
